pas_rfc_basics/__init__.py
pas_rfc_basics/date_time.py
pas_rfc_basics/header.py
pas_rfc_basics-1.0.0.data/data/docs/LICENSE
pas_rfc_basics-1.0.0.data/data/docs/README
pas_rfc_basics-1.0.0.dist-info/LICENSE
pas_rfc_basics-1.0.0.dist-info/METADATA
pas_rfc_basics-1.0.0.dist-info/WHEEL
pas_rfc_basics-1.0.0.dist-info/top_level.txt
pas_rfc_basics-1.0.0.dist-info/RECORD
